assets/authentication.png
assets/colab_usage.gif
assets/full_viz.png
assets/jupyter.gif
assets/load_ext.png
assets/sample_jupyter.png
frontend/.babelrc.js
frontend/.parcelrc
frontend/README.md
frontend/babel.config.js
frontend/jest-puppeteer.config.js
frontend/jest.config.js
frontend/package.json
frontend/tsconfig.json
frontend/src/app.js
frontend/src/graph-server.js
frontend/src/index.js
frontend/src/spanner-config.js
frontend/src/spanner-store.js
frontend/src/models/edge.js
frontend/src/models/graph-object.js
frontend/src/models/node.js
frontend/src/models/schema.js
frontend/src/visualization/spanner-forcegraph.js
frontend/src/visualization/spanner-menu.js
frontend/src/visualization/spanner-sidebar.js
frontend/src/visualization/spanner-table.js
frontend/static/dev.html
frontend/static/graph-bg.svg
frontend/static/jupyter.html
frontend/static/test.html
frontend/tests/jest.setup.ts
frontend/tests/mock-data.json
frontend/tests/serve-content.js
frontend/tests/unit/graph-server.test.ts
frontend/tests/unit/spanner-config.test.ts
frontend/tests/unit/spanner-store.test.ts
frontend/tests/unit/models/edge.test.ts
frontend/tests/unit/models/graph-object.test.ts
frontend/tests/unit/models/node.test.ts
frontend/tests/unit/models/schema.test.ts
frontend/tests/unit/visualization/spanner-menu.test.ts
frontend/tests/unit/visualization/spanner-sidebar.test.ts
frontend/tests/unit/visualization/spanner-table.test.ts
frontend/tests/visual/app.test.ts
frontend/tests/visual/jest-visual.setup.ts
frontend/tests/visual/visualization/spanner-forcegraph.test.ts
frontend/tests/visual/visualization/spanner-menu.test.ts
frontend/tests/visual/visualization/spanner-sidebar.test.ts
frontend/tests/visual/visualization/spanner-table.test.ts
spanner_graph_notebook-1.1.7.dist-info/licenses/LICENSE
spanner_graphs/__init__.py
spanner_graphs/cloud_database.py
spanner_graphs/conversion.py
spanner_graphs/database.py
spanner_graphs/exec_env.py
spanner_graphs/graph_entities.py
spanner_graphs/graph_mock_data.csv
spanner_graphs/graph_mock_schema.json
spanner_graph_notebook-1.1.7.dist-info/METADATA
spanner_graph_notebook-1.1.7.dist-info/WHEEL
spanner_graph_notebook-1.1.7.dist-info/top_level.txt
spanner_graph_notebook-1.1.7.dist-info/RECORD
