Metadata-Version: 2.4
Name: spanner-graph-notebook
Version: 1.1.7
Summary: Visually query Spanner Graph data in notebooks.
License-File: LICENSE
Requires-Dist: networkx
Requires-Dist: numpy
Requires-Dist: google-cloud-spanner
Requires-Dist: ipython
Requires-Dist: ipywidgets
Requires-Dist: notebook
Requires-Dist: requests
Requires-Dist: portpicker
Requires-Dist: pydata-google-auth
Dynamic: description
Dynamic: description-content-type
Dynamic: license-file
Dynamic: requires-dist
Dynamic: summary
